[
  {
    "date": [
      2017,
      11,
      20
    ],
    "level": 46.5
  },
  {
    "date": [
      2017,
      11,
      22
    ],
    "level": 44.5
  },
  {
    "date": [
      2017,
      11,
      26
    ],
    "level": 39.0
  },
  {
    "date": [
      2017,
      11,
      29
    ],
    "level": 37.0
  },
  {
    "date": [
      2017,
      12,
      2
    ],
    "level": 34.0
  },
  {
    "date": [
      2017,
      12,
      3
    ],
    "level": 28.75
  },
  {
    "date": [
      2017,
      12,
      4
    ],
    "level": 27.5
  },
  {
    "date": [
      2017,
      12,
      5
    ],
    "level": 27.0
  },
  {
    "date": [
      2017,
      12,
      6
    ],
    "level": 26.1875
  },
  {
    "date": [
      2017,
      12,
      7
    ],
    "level": 24.0
  },
  {
    "date": [
      2017,
      12,
      8
    ],
    "level": 23.625
  },
  {
    "date": [
      2017,
      12,
      10
    ],
    "level": 20.125
  }
]